<?xml version="1.0" ?>
< ROWDATA >
一二三
< ROW >
  <ID>5</ID>
  <NAME>&#30333;&#39592;&#31934;</NAME>
  <JOB>&#22934;&#24618;</JOB>
  <TESTCLOB>&lt;CLOB&gt;</TESTCLOB>
  <TESTDATE></TESTDATE>
</ROW>
456
<ROW>
  <ID>7</ID>
  <NAME>&#40657;&#29066;&#24618;</NAME>
  <JOB>&#22934;&#24618;</JOB>
  <TESTCLOB>&lt;CLOB&gt;</TESTCLOB>
  <TESTDATE></TESTDATE>
</ROW>
789
<ROW>
  <ID>19</ID>
  <NAME>&#32418;&#22825;&#29436;</NAME>
  <JOB>&#22934;&#24618;</JOB>
  <TESTCLOB>&lt;CLOB&gt;</TESTCLOB>
  <TESTDATE></TESTDATE>
</ROW>

</ROWDATA>
